model_compressor/VERSION.txt
model_compressor/__init__.py
model_compressor/api.py
model_compressor/typing.py
model_compressor/docs/__init__.py
model_compressor/docs/api.py
model_compressor/docs/typing.py
furiosa_model_compressor-2025.3.0.dist-info/METADATA
furiosa_model_compressor-2025.3.0.dist-info/WHEEL
furiosa_model_compressor-2025.3.0.dist-info/RECORD
